odoo/addons/sale_order_product_recommendation/README.rst
odoo/addons/sale_order_product_recommendation/__init__.py
odoo/addons/sale_order_product_recommendation/__manifest__.py
odoo/addons/sale_order_product_recommendation/i18n/es.po
odoo/addons/sale_order_product_recommendation/i18n/fr.po
odoo/addons/sale_order_product_recommendation/i18n/it.po
odoo/addons/sale_order_product_recommendation/i18n/pt_BR.po
odoo/addons/sale_order_product_recommendation/i18n/sale_order_product_recommendation.pot
odoo/addons/sale_order_product_recommendation/models/__init__.py
odoo/addons/sale_order_product_recommendation/models/res_company.py
odoo/addons/sale_order_product_recommendation/models/res_config_settings.py
odoo/addons/sale_order_product_recommendation/readme/CONFIGURE.md
odoo/addons/sale_order_product_recommendation/readme/CONTRIBUTORS.md
odoo/addons/sale_order_product_recommendation/readme/DESCRIPTION.md
odoo/addons/sale_order_product_recommendation/readme/USAGE.md
odoo/addons/sale_order_product_recommendation/security/ir.model.access.csv
odoo/addons/sale_order_product_recommendation/static/description/icon.png
odoo/addons/sale_order_product_recommendation/static/description/index.html
odoo/addons/sale_order_product_recommendation/tests/__init__.py
odoo/addons/sale_order_product_recommendation/tests/test_recommendation.py
odoo/addons/sale_order_product_recommendation/tests/test_recommendation_common.py
odoo/addons/sale_order_product_recommendation/views/res_config_settings_views.xml
odoo/addons/sale_order_product_recommendation/views/sale_order_view.xml
odoo/addons/sale_order_product_recommendation/wizards/__init__.py
odoo/addons/sale_order_product_recommendation/wizards/sale_order_recommendation.py
odoo/addons/sale_order_product_recommendation/wizards/sale_order_recommendation_view.xml
odoo_addon_sale_order_product_recommendation-18.0.1.1.2.dist-info/METADATA
odoo_addon_sale_order_product_recommendation-18.0.1.1.2.dist-info/WHEEL
odoo_addon_sale_order_product_recommendation-18.0.1.1.2.dist-info/top_level.txt
odoo_addon_sale_order_product_recommendation-18.0.1.1.2.dist-info/RECORD
