Metadata-Version: 2.1
Name: odoo-addon-sale_order_product_recommendation
Version: 18.0.1.1.2
Requires-Python: >=3.10
Requires-Dist: odoo==18.0.*
Summary: Recommend products to sell to customer based on history
Home-page: https://github.com/OCA/sale-workflow
License: AGPL-3
Author: Tecnativa, Odoo Community Association (OCA)
Author-email: support@odoo-community.org
Classifier: Programming Language :: Python
Classifier: Framework :: Odoo
Classifier: Framework :: Odoo :: 18.0
Classifier: License :: OSI Approved :: GNU Affero General Public License v3
